{
    "created_time": "2022-03-11T05:09:39Z",
    "files": [
        {
            "attachment_folder": "",
            "created_time": "2022-03-11T05:09:39Z",
            "id": "83",
            "modified_time": "2022-03-11T05:09:39Z",
            "name": "汉字.md",
            "signature": "67535712737683",
            "tags": [
            ]
        }
    ],
    "folders": [
    ],
    "id": "82",
    "modified_time": "2022-03-11T05:09:39Z",
    "signature": "82331875072403",
    "version": 3
}
